nzku/__init__.py
nzku/__main__.py
nzku/__version__.py
nzku/_logging.py
nzku-0a0.dev0.data/data/LICENSE.txt
nzku-0a0.dev0.data/data/requirements.txt
nzku-0a0.dev0.dist-info/LICENSE.txt
nzku-0a0.dev0.dist-info/METADATA
nzku-0a0.dev0.dist-info/WHEEL
nzku-0a0.dev0.dist-info/entry_points.txt
nzku-0a0.dev0.dist-info/top_level.txt
nzku-0a0.dev0.dist-info/RECORD
