Metadata-Version: 2.1
Name: nzku
Version: 0a0.dev0
Summary: Python package generated from template https://framagit.org/1ohmatr/sw/py/template
Home-page: https://framagit.org/1ohmatr/sw/py/nzku.git
Author: neze
Author-email: neze_nzku@melix.org
License: UNKNOWN
Platform: UNKNOWN
Classifier: Programming Language :: Python :: 3
Classifier: License :: OSI Approved :: MIT License
